<?xml version="1.0" encoding="utf-8" ?><dwsync><file name="blank.gif" server="files.000webhost.com" local="3441147042" remote="3589500000" Dst="-1" /><file name="fancybox_overlay.png" server="files.000webhost.com" local="3441147042" remote="3589500000" Dst="-1" /><file name="fancybox_loading.gif" server="files.000webhost.com" local="3441147042" remote="3589500000" Dst="-1" /><file name="fancybox_sprite.png" server="files.000webhost.com" local="3441147042" remote="3589500000" Dst="-1" /><file name="jquery.fancybox.css" server="files.000webhost.com" local="3588455808" remote="3589500000" Dst="-1" /><file name="fancybox_overlay.png" server="cavedarr.com" local="3441147042" remote="3591816780" Dst="-1" /><file name="blank.gif" server="cavedarr.com" local="3441147042" remote="3591816780" Dst="-1" /><file name="fancybox_loading.gif" server="cavedarr.com" local="3441147042" remote="3591816780" Dst="-1" /><file name="fancybox_sprite.png" server="cavedarr.com" local="3441147042" remote="3591816780" Dst="-1" /><file name="jquery.fancybox.css" server="cavedarr.com" local="3588455808" remote="3591816780" Dst="-1" /><file name="blank.gif" server="cavedarr.com//public_html/" local="3441147042" remote="3592637040" Dst="-1" /><file name="fancybox_loading.gif" server="cavedarr.com//public_html/" local="3441147042" remote="3592637040" Dst="-1" /><file name="fancybox_overlay.png" server="cavedarr.com//public_html/" local="3441147042" remote="3592637040" Dst="-1" /><file name="fancybox_sprite.png" server="cavedarr.com//public_html/" local="3441147042" remote="3592637040" Dst="-1" /><file name="jquery.fancybox.css" server="cavedarr.com//public_html/" local="3588455808" remote="3592637040" Dst="-1" /></dwsync>